acuiferoec/__init__.py
acuiferoec/acuifero.py
acuiferoec-0.1.0.dist-info/LICENSE
acuiferoec-0.1.0.dist-info/METADATA
acuiferoec-0.1.0.dist-info/WHEEL
acuiferoec-0.1.0.dist-info/top_level.txt
acuiferoec-0.1.0.dist-info/RECORD
